datavillage_sdk/.github/workflows/ci-master.yml
datavillage_sdk/__init__.py
datavillage_sdk/management/__init__.py
datavillage_sdk/management/auth.py
datavillage_sdk/management/consent.py
datavillage_sdk/management/sources.py
datavillage_sdk/user/__init__.py
datavillage_sdk/user/behaviour.py
datavillage_sdk/user/cages.py
datavillage_sdk-0.1.3.dist-info/LICENSE
datavillage_sdk-0.1.3.dist-info/WHEEL
datavillage_sdk-0.1.3.dist-info/METADATA
datavillage_sdk-0.1.3.dist-info/RECORD
